peakrdl_regblock_vhdl/__about__.py
peakrdl_regblock_vhdl/__init__.py
peakrdl_regblock_vhdl/__peakrdl__.py
peakrdl_regblock_vhdl/addr_decode.py
peakrdl_regblock_vhdl/dereferencer.py
peakrdl_regblock_vhdl/exporter.py
peakrdl_regblock_vhdl/external_acks.py
peakrdl_regblock_vhdl/forloop_generator.py
peakrdl_regblock_vhdl/identifier_filter.py
peakrdl_regblock_vhdl/module_tmpl.vhd
peakrdl_regblock_vhdl/package_tmpl.vhd
peakrdl_regblock_vhdl/parity.py
peakrdl_regblock_vhdl/scan_design.py
peakrdl_regblock_vhdl/struct_generator.py
peakrdl_regblock_vhdl/utils.py
peakrdl_regblock_vhdl/validate_design.py
peakrdl_regblock_vhdl/vhdl_int.py
peakrdl_regblock_vhdl/cpuif/__init__.py
peakrdl_regblock_vhdl/cpuif/base.py
peakrdl_regblock_vhdl/cpuif/apb3/__init__.py
peakrdl_regblock_vhdl/cpuif/apb3/apb3_tmpl.vhd
peakrdl_regblock_vhdl/cpuif/apb4/__init__.py
peakrdl_regblock_vhdl/cpuif/apb4/apb4_tmpl.vhd
peakrdl_regblock_vhdl/cpuif/avalon/__init__.py
peakrdl_regblock_vhdl/cpuif/avalon/avalon_tmpl.vhd
peakrdl_regblock_vhdl/cpuif/axi4lite/__init__.py
peakrdl_regblock_vhdl/cpuif/axi4lite/axi4lite_tmpl.vhd
peakrdl_regblock_vhdl/cpuif/obi/__init__.py
peakrdl_regblock_vhdl/cpuif/obi/obi_tmpl.vhd
peakrdl_regblock_vhdl/cpuif/passthrough/__init__.py
peakrdl_regblock_vhdl/cpuif/passthrough/passthrough_tmpl.vhd
peakrdl_regblock_vhdl/field_logic/__init__.py
peakrdl_regblock_vhdl/field_logic/bases.py
peakrdl_regblock_vhdl/field_logic/generators.py
peakrdl_regblock_vhdl/field_logic/hw_interrupts.py
peakrdl_regblock_vhdl/field_logic/hw_interrupts_with_write.py
peakrdl_regblock_vhdl/field_logic/hw_set_clr.py
peakrdl_regblock_vhdl/field_logic/hw_write.py
peakrdl_regblock_vhdl/field_logic/sw_onread.py
peakrdl_regblock_vhdl/field_logic/sw_onwrite.py
peakrdl_regblock_vhdl/field_logic/sw_singlepulse.py
peakrdl_regblock_vhdl/field_logic/templates/counter_macros_tmpl.vhd
peakrdl_regblock_vhdl/field_logic/templates/external_block_tmpl.vhd
peakrdl_regblock_vhdl/field_logic/templates/external_reg_tmpl.vhd
peakrdl_regblock_vhdl-1.2.0.0.dist-info/licenses/LICENSE
peakrdl_regblock_vhdl-1.2.0.0.dist-info/METADATA
peakrdl_regblock_vhdl-1.2.0.0.dist-info/WHEEL
peakrdl_regblock_vhdl-1.2.0.0.dist-info/entry_points.txt
peakrdl_regblock_vhdl-1.2.0.0.dist-info/top_level.txt
peakrdl_regblock_vhdl-1.2.0.0.dist-info/RECORD
