Metadata-Version: 2.4
Name: peakrdl-regblock-vhdl
Version: 1.2.0.0
Summary: Compile SystemRDL into a VHDL control/status register (CSR) block
Author: Alex Mykyta
Maintainer: Dana Sorensen
License: LGPLv3
Project-URL: Source, https://github.com/SystemRDL/PeakRDL-regblock-vhdl
Project-URL: Tracker, https://github.com/SystemRDL/PeakRDL-regblock-vhdl/issues
Project-URL: Changelog, https://github.com/SystemRDL/PeakRDL-regblock-vhdl/releases
Project-URL: Documentation, https://peakrdl-regblock-vhdl.readthedocs.io/
Keywords: SystemRDL,PeakRDL,CSR,compiler,tool,registers,generator,VHDL,register abstraction layer,FPGA,ASIC
Classifier: Development Status :: 4 - Beta
Classifier: Programming Language :: Python
Classifier: Programming Language :: Python :: 3
Classifier: Programming Language :: Python :: 3 :: Only
Classifier: Intended Audience :: Developers
Classifier: License :: OSI Approved :: GNU Lesser General Public License v3 (LGPLv3)
Classifier: Operating System :: OS Independent
Classifier: Topic :: Scientific/Engineering :: Electronic Design Automation (EDA)
Requires-Python: >=3.7
License-File: LICENSE
Requires-Dist: systemrdl-compiler~=1.29
Requires-Dist: Jinja2>=2.11
Requires-Dist: importlib-resources>=5.12.0
Provides-Extra: cli
Requires-Dist: peakrdl-cli>=1.2.3; extra == "cli"
Dynamic: license-file
